viewforge/__init__.py
viewforge/core.py
viewforge-0.1.0.dist-info/licenses/LICENSE
viewforge-0.1.0.dist-info/METADATA
viewforge-0.1.0.dist-info/WHEEL
viewforge-0.1.0.dist-info/top_level.txt
viewforge-0.1.0.dist-info/RECORD
