Metadata-Version: 2.4
Name: viewforge
Version: 0.1.0
Summary: A modular Python UI and workflow engine.
Author-email: Israel Dryer <israel.dryer@appforia.net>
License: GPL-3.0-or-later
Project-URL: Homepage, https://github.com/appforia/viewforge
Project-URL: Documentation, https://yourdocs.com/viewforge
Project-URL: Source, https://github.com/appforia/viewforge
Requires-Python: >=3.7
License-File: LICENSE
Dynamic: license-file
